{
  "name": "Varneon - VUdon",
  "author": "https://github.com/Varneon",
  "url": "https://Varneon.github.io/Repositories/vpm/vudon.json",
  "packages": {
    "com.varneon.vudon.depth-buffer-toolkit": {
      "versions": {
        "0.1.0": {
          "name": "com.varneon.vudon.depth-buffer-toolkit",
          "version": "0.1.0",
          "displayName": "VUdon - Depth Buffer Toolkit",
          "description": "A toolkit for configuring the depth buffer in VRChat worlds with Udon",
          "unity": "2019.4",
          "unityRelease": "31f1",
          "author": {
            "name": "Varneon",
            "url": "https://github.com/Varneon"
          },
          "dependencies": {
            "com.vrchat.udonsharp": "1.0.1"
          },
          "vpmDependencies": {
            "com.vrchat.udonsharp": "1.x.x"
          },
          "url": "https://github.com/Varneon/VUdon-DepthBufferToolkit/releases/download/0.1.0/com.varneon.vudon.depth-buffer-toolkit-0.1.0.zip?download"
        }
      }
    },
    "com.varneon.vudon.seats": {
      "versions": {
        "0.0.1": {
          "name": "com.varneon.vudon.seats",
          "displayName": "VUdon - Seats",
          "version": "0.0.1",
          "unity": "2019.4",
          "unityRelease": "29f1",
          "description": "Self-calibrating synced abstract seats with callbacks and API",
          "author": {
            "name": "Varneon",
            "url": "https://github.com/Varneon"
          },
          "dependencies": {
            "com.vrchat.udonsharp": "1.0.1"
          },
          "vpmDependencies": {
            "com.vrchat.udonsharp": "1.x.x"
          },
          "url": "https://github.com/Varneon/VUdon-Seats/releases/download/0.0.1/com.varneon.vudon.seats-0.0.1.zip?download"
        }
      }
    },
    "com.varneon.vudon.array-extensions": {
      "versions": {
        "0.1.0": {
          "name": "com.varneon.vudon.array-extensions",
          "version": "0.1.0",
          "displayName": "VUdon - Array Extensions",
          "description": "Collection of array extension methods compatible with UdonSharp 1.x which adds partial feature set from List<T>",
          "unity": "2019.4",
          "unityRelease": "31f1",
          "author": {
            "name": "Varneon",
            "url": "https://github.com/Varneon"
          },
          "vpmDependencies": {
            "com.vrchat.udonsharp": "1.x.x"
          },
          "url": "https://github.com/Varneon/VUdon-ArrayExtensions/releases/download/0.1.0/com.varneon.vudon.array-extensions-0.1.0.zip?download"
        }
      }
    },
    "com.varneon.vudon.visibility-sensors": {
      "versions": {
        "0.0.1": {
          "name": "com.varneon.vudon.visibility-sensors",
          "displayName": "VUdon - Visibility Sensors",
          "version": "0.0.1",
          "unity": "2019.4",
          "unityRelease": "29f1",
          "description": "Various sensors for detecting a renderer's visibility state and relaying it to e.g. GameObject's active state, UdonBehaviour variables, etc.",
          "author": {
            "name": "Varneon",
            "url": "https://github.com/Varneon"
          },
          "dependencies": {
            "com.vrchat.udonsharp": "1.0.1"
          },
          "vpmDependencies": {
            "com.vrchat.udonsharp": "1.x.x"
          },
          "url": "https://github.com/Varneon/VUdon-VisibilitySensors/releases/download/0.0.1/com.varneon.vudon.visibility-sensors-0.0.1.zip?download"
        }
      }
    }
  }
}